Metadata-Version: 2.1
Name: speclear
Version: 0.1.1
Summary: speclear - delete specific history in major windows browsers
Home-page: https://github.com/Shivanshu26shiv/speclear
Author: Shivanshu Srivastava
Author-email: shivanshu26shiv@gmail.com
License: MIT
Download-URL: https://github.com/Shivanshu26shiv/speclear/archive/v_0.1.1.tar.gz
Keywords: browser,browser history,chrome,firefox,opera,safari,ie
Platform: UNKNOWN
Classifier: Development Status :: 3 - Alpha
Classifier: Intended Audience :: Developers
Classifier: Topic :: Software Development :: Build Tools
Classifier: Operating System :: Microsoft :: Windows
Classifier: License :: OSI Approved :: MIT License
Classifier: Programming Language :: Python :: 3
Classifier: Programming Language :: Python :: 3.4
Classifier: Programming Language :: Python :: 3.5
Classifier: Programming Language :: Python :: 3.6
